dataspine_serving_grpc/__init__.py
dataspine_serving_grpc/serving.py
dataspine_serving_grpc-0.1.dist-info/DESCRIPTION.rst
dataspine_serving_grpc-0.1.dist-info/METADATA
dataspine_serving_grpc-0.1.dist-info/RECORD
dataspine_serving_grpc-0.1.dist-info/WHEEL
dataspine_serving_grpc-0.1.dist-info/metadata.json
dataspine_serving_grpc-0.1.dist-info/top_level.txt
