Metadata-Version: 2.0
Name: dataspine-serving-grpc
Version: 0.1
Summary: Dataspine Serving gRPC Library
Home-page: https://github.com/dataspine
Author: Dataspine, Inc
Author-email: dev@dataspine.io
License: UNKNOWN
Platform: UNKNOWN
Requires-Dist: grpcio (>=1.0)
Requires-Dist: tensorflow (==1.8.0)
Requires-Dist: tensorflow-serving-api (==1.13.0)
